setup.py
dsn_probability/Binomialdistribution.py
dsn_probability/Gaussiandistribution.py
dsn_probability/Generaldistribution.py
dsn_probability/__init__.py
dsn_probability.egg-info/PKG-INFO
dsn_probability.egg-info/SOURCES.txt
dsn_probability.egg-info/dependency_links.txt
dsn_probability.egg-info/not-zip-safe
dsn_probability.egg-info/top_level.txt