Metadata-Version: 1.0
Name: dsn-probability
Version: 1.2
Summary: Gaussian and Binomial distributions
Home-page: UNKNOWN
Author: Maryam Sikander
Author-email: maryamsikander@gmail.com
License: UNKNOWN
Platform: UNKNOWN
